MANIFEST.in
README.rst
setup.cfg
setup.py
ckanext/__init__.py
ckanext/userautoadd/__init__.py
ckanext/userautoadd/plugin.py
ckanext/userautoadd/logic/__init__.py
ckanext/userautoadd/logic/action/__init__.py
ckanext/userautoadd/logic/action/create.py
ckanext/userautoadd/tests/__init__.py
ckanext/userautoadd/tests/logic/__init__.py
ckanext/userautoadd/tests/logic/action/__init__.py
ckanext/userautoadd/tests/logic/action/test_create.py
ckanext_userautoadd.egg-info/PKG-INFO
ckanext_userautoadd.egg-info/SOURCES.txt
ckanext_userautoadd.egg-info/dependency_links.txt
ckanext_userautoadd.egg-info/entry_points.txt
ckanext_userautoadd.egg-info/pbr.json
ckanext_userautoadd.egg-info/top_level.txt