Metadata-Version: 1.1
Name: ckanext-userautoadd
Version: 1.0.1
Summary: CKAN extension to add new users to groups and organisations
Home-page: https://github.com/aptivate/ckanext-userautoadd
Author: Aptivate
Author-email: mapaction-team@aptivate.org
License: AGPL
Keywords: CKAN user organization group
Platform: UNKNOWN
Classifier: Development Status :: 4 - Beta
Classifier: License :: OSI Approved :: GNU Affero General Public License v3 or later (AGPLv3+)
Classifier: Programming Language :: Python :: 2.6
Classifier: Programming Language :: Python :: 2.7
